{
  "Group": [
    {
      "Title": "Lorem Ipsum Delore",
      "Description": "lorem ipsum",
      "icon": ""
    },
    {
      "Title": "Accusamus et iusto",
      "Description": "quis nostrud exercitation",
      "icon": ""
    },
    {
      "Title": "Odio dignissimos",
      "Description": "Ut enim ad minim",
      "icon": ""
    },
    {
      "Title": "Ducimus blanditiis",
      "Description": "dolore magna aliqua",
      "icon": ""
    },
    {
      "Title": "Nam libero tempore",
      "Description": "incididunt ut labore",
      "icon": ""
    },
    {
      "Title": "Soluta nobis est",
      "Description": "sed do eiusmod tempor",
      "icon": ""
    },
    {
      "Title": "Officia deserunt",
      "Description": "consectetur adipiscing elit",
      "icon": ""
    },
    {
      "Title": "Mollitia animi id",
      "Description": "dolor sit amet",
      "icon": ""
    }
  ]
}